wataash_utils/__init__.py
wataash_utils/_exp.py
wataash_utils/argparse.py
wataash_utils/click.py
wataash_utils/collections.py
wataash_utils/json.py
wataash_utils/logger.py
wataash_utils/logging.py
wataash_utils/pycharm.py
wataash_utils/python.py
wataash_utils/requests.py
wataash_utils/selenium.py
wataash_utils/str.py
wataash_utils-0.5.0.dist-info/LICENSE
wataash_utils-0.5.0.dist-info/METADATA
wataash_utils-0.5.0.dist-info/WHEEL
wataash_utils-0.5.0.dist-info/top_level.txt
wataash_utils-0.5.0.dist-info/RECORD
